hybparsimony/__init__.py
hybparsimony/hybparsimony.py
hybparsimony/lhs/__init__.py
hybparsimony/lhs/base/__init__.py
hybparsimony/lhs/base/geneticLHS.py
hybparsimony/lhs/base/improvedLHS.py
hybparsimony/lhs/base/maximinLHS.py
hybparsimony/lhs/base/optimumLHS.py
hybparsimony/lhs/base/randomLHS.py
hybparsimony/lhs/util/__init__.py
hybparsimony/lhs/util/bclib.py
hybparsimony/lhs/util/utilityLHS.py
hybparsimony/util/__init__.py
hybparsimony/util/complexity.py
hybparsimony/util/fitness.py
hybparsimony/util/hyb_aux.py
hybparsimony/util/models.py
hybparsimony/util/order.py
hybparsimony/util/parsimony_monitor.py
hybparsimony/util/population.py
hybparsimony-0.0.5.dist-info/METADATA
hybparsimony-0.0.5.dist-info/WHEEL
hybparsimony-0.0.5.dist-info/licenses/LICENSE
hybparsimony-0.0.5.dist-info/RECORD
