Metadata-Version: 2.4
Name: hybparsimony
Version: 0.0.5
Project-URL: Homepage, https://github.com/jodivaso/hybparsimony
Author-email: Jose Divasón <jose.divason@unirioja.es>, Francisco Javier Martínez de Pisón <fjmartin@unirioja.es>
License-File: LICENSE
Classifier: License :: OSI Approved :: MIT License
Classifier: Operating System :: OS Independent
Classifier: Programming Language :: Python :: 3
Requires-Python: >=3.9
Requires-Dist: dill
Requires-Dist: pandas
Requires-Dist: scikit-learn
